NonlinearTMM-1.3.11.dist-info/RECORD
NonlinearTMM-1.3.11.dist-info/WHEEL
NonlinearTMM-1.3.11.dist-info/top_level.txt
NonlinearTMM-1.3.11.dist-info/METADATA
NonlinearTMM-1.3.11.dist-info/LICENSE
NonlinearTMM/_Material.py
NonlinearTMM/__init__.py
NonlinearTMM/_SecondOrderNLTMMCython.cpython-310-x86_64-linux-gnu.so
NonlinearTMM/_NonlinearTMM.py
NonlinearTMM/_SecondOrderNLTMM.py
NonlinearTMM.libs/libgomp-a34b3233.so.1.0.0
