Metadata-Version: 2.1
Name: NonlinearTMM
Version: 1.3.11
Summary: Nonlinear transfer matrix method
Home-page: https://github.com/ardiloot/NonlinearTMM
Author: Ardi Loot
Author-email: ardi.loot@outlook.com
Requires-Python: >=3.5
License-File: LICENSE
Requires-Dist: numpy
Requires-Dist: scipy
Requires-Dist: eigency (>=2.0.0)
Provides-Extra: dev
Requires-Dist: pyyaml ; extra == 'dev'
Requires-Dist: pytest ; extra == 'dev'
Requires-Dist: flake8 ; extra == 'dev'
Requires-Dist: pip-tools ; extra == 'dev'
Requires-Dist: matplotlib ; extra == 'dev'
Provides-Extra: test
Requires-Dist: pyyaml ; extra == 'test'
Requires-Dist: pytest ; extra == 'test'
Requires-Dist: flake8 ; extra == 'test'
